edx_django_utils/__init__.py
edx_django_utils/apps.py
edx_django_utils/admin/mixins.py
edx_django_utils/admin/tests/__init__.py
edx_django_utils/admin/tests/models.py
edx_django_utils/admin/tests/test_mixins.py
edx_django_utils/cache/__init__.py
edx_django_utils/cache/middleware.py
edx_django_utils/cache/utils.py
edx_django_utils/cache/tests/__init__.py
edx_django_utils/cache/tests/test_middleware.py
edx_django_utils/cache/tests/test_utils.py
edx_django_utils/data_generation/__init__.py
edx_django_utils/data_generation/management/__init__.py
edx_django_utils/data_generation/management/commands/__init__.py
edx_django_utils/data_generation/management/commands/manufacture_data.py
edx_django_utils/data_generation/tests/__init__.py
edx_django_utils/data_generation/tests/apps.py
edx_django_utils/data_generation/tests/factories.py
edx_django_utils/data_generation/tests/models.py
edx_django_utils/data_generation/tests/test_management.py
edx_django_utils/db/__init__.py
edx_django_utils/db/queryset_utils.py
edx_django_utils/db/read_replica.py
edx_django_utils/db/tests/__init__.py
edx_django_utils/db/tests/test_queryset_utils.py
edx_django_utils/db/tests/test_read_replica.py
edx_django_utils/ip/__init__.py
edx_django_utils/ip/internal/__init__.py
edx_django_utils/ip/internal/ip.py
edx_django_utils/ip/internal/tests/__init__.py
edx_django_utils/ip/internal/tests/test_ip.py
edx_django_utils/logging/__init__.py
edx_django_utils/logging/internal/__init__.py
edx_django_utils/logging/internal/filters.py
edx_django_utils/logging/internal/log_sensitive.py
edx_django_utils/logging/tests/__init__.py
edx_django_utils/logging/tests/test_log_sensitive.py
edx_django_utils/logging/tests/test_logging.py
edx_django_utils/monitoring/__init__.py
edx_django_utils/monitoring/signals.py
edx_django_utils/monitoring/utils.py
edx_django_utils/monitoring/internal/__init__.py
edx_django_utils/monitoring/internal/backends.py
edx_django_utils/monitoring/internal/middleware.py
edx_django_utils-8.0.1.dist-info/licenses/LICENSE.txt
edx_django_utils-8.0.1.dist-info/METADATA
edx_django_utils-8.0.1.dist-info/WHEEL
edx_django_utils-8.0.1.dist-info/entry_points.txt
edx_django_utils-8.0.1.dist-info/top_level.txt
edx_django_utils-8.0.1.dist-info/RECORD
