Metadata-Version: 2.4
Name: edx-django-utils
Version: 8.0.1
Summary: EdX utilities for Django Application development.
Home-page: https://github.com/openedx/edx-django-utils
Author: edX
Author-email: oscm@edx.org
Keywords: Django edx
Classifier: Development Status :: 3 - Alpha
Classifier: Framework :: Django
Classifier: Framework :: Django :: 4.2
Classifier: Framework :: Django :: 5.2
Classifier: Intended Audience :: Developers
Classifier: License :: OSI Approved :: Apache Software License
Classifier: Natural Language :: English
Classifier: Programming Language :: Python :: 3
Classifier: Programming Language :: Python :: 3.12
License-File: LICENSE.txt
Requires-Dist: Django
Requires-Dist: PyNaCl
Requires-Dist: click
Requires-Dist: django-crum
Requires-Dist: django-waffle
Requires-Dist: psutil
Requires-Dist: stevedore
Dynamic: author
Dynamic: author-email
Dynamic: classifier
Dynamic: description
Dynamic: description-content-type
Dynamic: home-page
Dynamic: keywords
Dynamic: license-file
Dynamic: requires-dist
Dynamic: summary
